LICENSE.txt
README.txt
bootstrap.py
buildout.cfg
setup.py
src/jquery/__init__.py
src/jquery.jsonform.egg-info/PKG-INFO
src/jquery.jsonform.egg-info/SOURCES.txt
src/jquery.jsonform.egg-info/dependency_links.txt
src/jquery.jsonform.egg-info/namespace_packages.txt
src/jquery.jsonform.egg-info/not-zip-safe
src/jquery.jsonform.egg-info/requires.txt
src/jquery.jsonform.egg-info/top_level.txt
src/jquery/jsonform/README.txt
src/jquery/jsonform/SETUP.cfg
src/jquery/jsonform/TODO.txt
src/jquery/jsonform/__init__.py
src/jquery/jsonform/browser.py
src/jquery/jsonform/configure.zcml
src/jquery/jsonform/jquery.jsonform-configure.zcml
src/jquery/jsonform/jsdoc.bat
src/jquery/jsonform/json.py
src/jquery/jsonform/jsonform.validate.css
src/jquery/jsonform/jsonform.validate.js
